{
  "artifact_2221429764": {
    "java_home": "extracted/jdk-24",
    "java_version_output": "openjdk 24-internal 2025-03-18\nOpenJDK Runtime Environment (build 24-internal-cafec0c0-88cd6e2d3e55cdd46ee63bd921dc08cc24c7147f)\nOpenJDK 64-Bit Server VM (build 24-internal-cafec0c0-88cd6e2d3e55cdd46ee63bd921dc08cc24c7147f, mixed mode, sharing)"
  },
  "status": "passed",
  "history": [],
  "datetime": "2024-11-21T22:57:52.076480+00:00",
  "url": "https://github.com/openjdk/jdk/pull/22280",
  "number": 22280,
  "title": "6726901: JDWP: ReferenceType.GetValues crashes jvm in case non-static fields are passed",
  "head_sha": "88cd6e2d3e55cdd46ee63bd921dc08cc24c7147f",
  "run_url": "https://github.com/dougxc/openjdk-pr-canary/actions/runs/11962776797"
}