{
  "artifact_1935670975": {
    "java_home": "extracted/jdk-24",
    "java_version_output": "openjdk 24-internal 2025-03-18\nOpenJDK Runtime Environment (build 24-internal-honkar-jdk-fa890150e5fc7321c6051bf06869b993c8a8433f)\nOpenJDK 64-Bit Server VM (build 24-internal-honkar-jdk-fa890150e5fc7321c6051bf06869b993c8a8433f, mixed mode, sharing)"
  },
  "status": "passed",
  "history": [
    {
      "artifact_1932004073": {
        "java_home": "extracted/jdk-24",
        "java_version_output": "openjdk 24-internal 2025-03-18\nOpenJDK Runtime Environment (build 24-internal-honkar-jdk-818df2ab2fe8511d6b4cacfd9e9baebc83b752ea)\nOpenJDK 64-Bit Server VM (build 24-internal-honkar-jdk-818df2ab2fe8511d6b4cacfd9e9baebc83b752ea, mixed mode, sharing)"
      },
      "status": "passed",
      "history": [],
      "datetime": "2024-09-13T22:59:30.186311",
      "url": "https://github.com/openjdk/jdk/pull/21005",
      "number": 21005,
      "title": "JDK-8339962 : Open source AWT TextField tests - Set1",
      "head_sha": "818df2ab2fe8511d6b4cacfd9e9baebc83b752ea",
      "run_url": "https://github.com/dougxc/openjdk-pr-canary/actions/runs/10857120866"
    }
  ],
  "datetime": "2024-09-16T03:06:30.757760",
  "url": "https://github.com/openjdk/jdk/pull/21005",
  "number": 21005,
  "title": "JDK-8339962 : Open source AWT TextField tests - Set1",
  "head_sha": "fa890150e5fc7321c6051bf06869b993c8a8433f",
  "run_url": "https://github.com/dougxc/openjdk-pr-canary/actions/runs/10876783701"
}