{
  "artifact_3088804663": {
    "java_home": "extracted/jdk-25",
    "java_version_output": "openjdk 25-internal 2025-09-16\nOpenJDK Runtime Environment (build 25-internal-mrserb-7a833461836957532b6f0dc001878d6633000d0b)\nOpenJDK 64-Bit Server VM (build 25-internal-mrserb-7a833461836957532b6f0dc001878d6633000d0b, mixed mode, sharing)"
  },
  "status": "passed",
  "history": [],
  "datetime": "2025-05-08T22:07:01.601349+00:00",
  "url": "https://github.com/openjdk/jdk/pull/25127",
  "number": 25127,
  "title": "8356571: Re-enable -Wtype-limits for GCC in LCMS",
  "head_sha": "7a833461836957532b6f0dc001878d6633000d0b",
  "run_url": "https://github.com/dougxc/openjdk-pr-canary/actions/runs/14916495082"
}