{
  "artifact_3489388483": {
    "java_home": "extracted/jdk-26",
    "java_version_output": "openjdk 26-internal 2026-03-17\nOpenJDK Runtime Environment (build 26-internal-liach-883a17120b777efec9e6579b00c23459f3c49f4d)\nOpenJDK 64-Bit Server VM (build 26-internal-liach-883a17120b777efec9e6579b00c23459f3c49f4d, mixed mode, sharing)"
  },
  "status": "passed",
  "history": [],
  "datetime": "2025-07-08T19:43:45.225662+00:00",
  "url": "https://github.com/openjdk/jdk/pull/26200",
  "number": 26200,
  "title": "8361615: CodeBuilder::parameterSlot throws undocumented IOOBE",
  "head_sha": "883a17120b777efec9e6579b00c23459f3c49f4d",
  "run_url": "https://github.com/dougxc/openjdk-pr-canary/actions/runs/16152503797"
}