{
  "artifact_2122032766": {
    "java_home": "extracted/jdk-24",
    "java_version_output": "openjdk 24-internal 2025-03-18\nOpenJDK Runtime Environment (build 24-internal-kabutz-5dc64f7ee613d2738c4abcf97aa79b81e7727f46)\nOpenJDK 64-Bit Server VM (build 24-internal-kabutz-5dc64f7ee613d2738c4abcf97aa79b81e7727f46, mixed mode, sharing)"
  },
  "status": "passed",
  "history": [],
  "datetime": "2024-10-30T09:59:38.921666+00:00",
  "url": "https://github.com/openjdk/jdk/pull/21783",
  "number": 21783,
  "title": "8343250: ArrayBlockingQueue serialization not thread safe",
  "head_sha": "5dc64f7ee613d2738c4abcf97aa79b81e7727f46",
  "run_url": "https://github.com/dougxc/openjdk-pr-canary/actions/runs/11590677328"
}