{
  "artifact_3571621480": {
    "java_home": "extracted/jdk-26",
    "java_version_output": "openjdk 26-internal 2026-03-17\nOpenJDK Runtime Environment (build 26-internal-Korov-931db213d453aa49242e41b340ea391b9eaf5a49)\nOpenJDK 64-Bit Server VM (build 26-internal-Korov-931db213d453aa49242e41b340ea391b9eaf5a49, mixed mode, sharing)"
  },
  "status": "passed",
  "history": [],
  "datetime": "2025-07-20T07:39:39.892744+00:00",
  "url": "https://github.com/openjdk/jdk/pull/26404",
  "number": 26404,
  "title": "8362658: sun/security/ssl/SSLEngineImpl/* tests duplicate jvm flags",
  "head_sha": "931db213d453aa49242e41b340ea391b9eaf5a49",
  "run_url": "https://github.com/dougxc/openjdk-pr-canary/actions/runs/16397446705"
}