{
  "artifact_2085643226": {
    "java_home": "extracted/jdk-24",
    "java_version_output": "openjdk 24-internal 2025-03-18\nOpenJDK Runtime Environment (build 24-internal-sashamatveev-97307d5c4385e9d1e5e446e94beb2364453ed875)\nOpenJDK 64-Bit Server VM (build 24-internal-sashamatveev-97307d5c4385e9d1e5e446e94beb2364453ed875, mixed mode, sharing)"
  },
  "status": "passed",
  "history": [],
  "datetime": "2024-10-22T03:06:37.151100+00:00",
  "url": "https://github.com/openjdk/jdk/pull/21628",
  "number": 21628,
  "title": "8341939: SigningOptionsTest fails without Xcode with command line developer tools after JDK-8341443",
  "head_sha": "97307d5c4385e9d1e5e446e94beb2364453ed875",
  "run_url": "https://github.com/dougxc/openjdk-pr-canary/actions/runs/11452342716"
}