{
  "artifact_3479976290": {
    "java_home": "extracted/jdk-26",
    "java_version_output": "openjdk 26-internal 2026-03-17\nOpenJDK Runtime Environment (build 26-internal-azvegint-7096b725b0a611250874292eca302bd3578828d1)\nOpenJDK 64-Bit Server VM (build 26-internal-azvegint-7096b725b0a611250874292eca302bd3578828d1, mixed mode, sharing)"
  },
  "status": "passed",
  "history": [],
  "datetime": "2025-07-07T19:37:53.711428+00:00",
  "url": "https://github.com/openjdk/jdk/pull/26170",
  "number": 26170,
  "title": "8360647: [XWayland] [OL10] NumPad keys are not triggered",
  "head_sha": "7096b725b0a611250874292eca302bd3578828d1",
  "run_url": "https://github.com/dougxc/openjdk-pr-canary/actions/runs/16126024526"
}