{
  "artifact_3772226290": {
    "java_home": "extracted/jdk-26",
    "java_version_output": "openjdk 26-internal 2026-03-17\nOpenJDK Runtime Environment (build 26-internal-toxaart-bf872c079737833d8602b9c341955523273ecf21)\nOpenJDK 64-Bit Server VM (build 26-internal-toxaart-bf872c079737833d8602b9c341955523273ecf21, mixed mode, sharing)"
  },
  "status": "passed",
  "history": [],
  "datetime": "2025-08-15T11:49:48.320309+00:00",
  "url": "https://github.com/openjdk/jdk/pull/26794",
  "number": 26794,
  "title": "8365556: ObjectMonitor::try_lock_or_add_to_entry_list() returns true with the wrong state of the node",
  "head_sha": "bf872c079737833d8602b9c341955523273ecf21",
  "run_url": "https://github.com/dougxc/openjdk-pr-canary/actions/runs/16989019158"
}