{
  "artifact_3064092924": {
    "java_home": "extracted/jdk-25",
    "java_version_output": "openjdk 25-internal 2025-09-16\nOpenJDK Runtime Environment (build 25-internal-minborg-116ce16ce02c2ad421be0b78d570e07f42ce0511)\nOpenJDK 64-Bit Server VM (build 25-internal-minborg-116ce16ce02c2ad421be0b78d570e07f42ce0511, mixed mode, sharing)"
  },
  "status": "passed",
  "history": [],
  "datetime": "2025-05-06T10:16:38.702589+00:00",
  "url": "https://github.com/openjdk/jdk/pull/25004",
  "number": 25004,
  "title": "8356080: Address post-integration comments for Stable Values",
  "head_sha": "116ce16ce02c2ad421be0b78d570e07f42ce0511",
  "run_url": "https://github.com/dougxc/openjdk-pr-canary/actions/runs/14856306716"
}