{
  "artifact_2044327064": {
    "java_home": "extracted/jdk-24",
    "java_version_output": "openjdk 24-internal 2025-03-18\nOpenJDK Runtime Environment (build 24-internal-eirbjo-661032c85257711583826b8f4ebdbc6161e6abff)\nOpenJDK 64-Bit Server VM (build 24-internal-eirbjo-661032c85257711583826b8f4ebdbc6161e6abff, mixed mode, sharing)"
  },
  "status": "passed",
  "history": [],
  "datetime": "2024-10-11T09:33:37.136473",
  "url": "https://github.com/openjdk/jdk/pull/21467",
  "number": 21467,
  "title": "8341944: zlib no longer requires dummy byte for raw inflate",
  "head_sha": "661032c85257711583826b8f4ebdbc6161e6abff",
  "run_url": "https://github.com/dougxc/openjdk-pr-canary/actions/runs/11289301053"
}