{
  "artifact_3615151707": {
    "java_home": "extracted/jdk-26",
    "java_version_output": "openjdk 26-internal 2026-03-17\nOpenJDK Runtime Environment (build 26-internal-tstuefe-c5542489b183acb3b938d719ccf00fc5ead49008)\nOpenJDK 64-Bit Server VM (build 26-internal-tstuefe-c5542489b183acb3b938d719ccf00fc5ead49008, mixed mode, sharing)"
  },
  "status": "passed",
  "history": [],
  "datetime": "2025-07-25T15:57:06.645022+00:00",
  "url": "https://github.com/openjdk/jdk/pull/26472",
  "number": 26472,
  "title": "8364004: Expose VMError::controlledCrash via Whitebox",
  "head_sha": "c5542489b183acb3b938d719ccf00fc5ead49008",
  "run_url": "https://github.com/dougxc/openjdk-pr-canary/actions/runs/16525800445"
}