{
  "artifact_3390038503": {
    "java_home": "extracted/jdk-26",
    "java_version_output": "openjdk 26-internal 2026-03-17\nOpenJDK Runtime Environment (build 26-internal-afshin-zafari-461a00ed90de490d1b5ea73daa083d62c96ce12e)\nOpenJDK 64-Bit Server VM (build 26-internal-afshin-zafari-461a00ed90de490d1b5ea73daa083d62c96ce12e, mixed mode, sharing)"
  },
  "status": "passed",
  "history": [],
  "datetime": "2025-06-24T08:53:04.338732+00:00",
  "url": "https://github.com/openjdk/jdk/pull/25950",
  "number": 25950,
  "title": "8360048: NMT crash in gtest/NMTGtests.java: fatal error: NMT corruption: Block at 0x0000017748307120: header canary broken",
  "head_sha": "461a00ed90de490d1b5ea73daa083d62c96ce12e",
  "run_url": "https://github.com/dougxc/openjdk-pr-canary/actions/runs/15845629550"
}